{"total":24235,"countries":{"null":15612,"DE":1416,"US":2481,"TH":37,"SE":103,"UA":33,"KR":130,"CH":239,"FI":394,"SG":135,"GB":315,"BR":108,"JP":138,"IT":106,"NL":356,"IE":52,"FR":595,"SA":7,"AT":94,"CZ":110,"MD":11,"BZ":1,"CA":381,"TW":31,"HR":8,"ES":110,"LT":41,"RU":181,"HK":56,"ID":29,"AU":177,"SI":17,"MY":20,"ZA":37,"PT":23,"DK":15,"HU":24,"RO":31,"IN":46,"PL":61,"CW":2,"EC":3,"AI":1,"AE":20,"GR":7,"DO":5,"RS":6,"KZ":6,"CN":45,"BE":47,"IS":12,"PH":5,"KG":2,"IL":5,"AD":3,"SK":25,"UZ":3,"JM":1,"AR":17,"NO":35,"EE":8,"UY":5,"TR":14,"BG":40,"PA":1,"CD":1,"CL":8,"NG":1,"MT":4,"ME":1,"MX":25,"PR":5,"IR":1,"SV":3,"CR":6,"AL":1,"VN":6,"NZ":34,"CO":6,"BY":8,"LI":2,"PK":1,"FO":2,"LU":9,"JE":1,"BH":5,"KW":2,"QA":4,"LV":4,"PY":1,"AM":1,"RE":1,"CY":3,"IM":2,"VE":2,"SR":1,"SC":1,"TT":1,"KH":1,"AW":1,"OM":1}}