{"total":22955,"countries":{"null":15365,"DE":1267,"US":2238,"AR":17,"RO":26,"FR":549,"SG":105,"IT":87,"NL":323,"CA":347,"GB":262,"FI":358,"IE":42,"ES":106,"AU":134,"CZ":103,"MD":10,"KR":99,"BZ":1,"AT":80,"MX":20,"JP":107,"SE":76,"BR":81,"DK":17,"IN":21,"RU":177,"UA":32,"ZA":26,"CH":218,"PL":64,"TH":33,"CO":4,"LT":38,"TW":22,"HU":29,"SK":20,"CN":43,"BE":27,"DO":3,"PT":18,"NZ":30,"HK":29,"NO":35,"CW":2,"ME":1,"ID":15,"IL":4,"RS":3,"SI":14,"MU":1,"JM":1,"HR":6,"EE":8,"BG":38,"MY":21,"IS":13,"TR":10,"LU":10,"KH":1,"AE":17,"GR":6,"IR":2,"CL":6,"MT":3,"CR":5,"AI":1,"PA":2,"KZ":4,"NG":1,"UY":4,"PR":7,"RE":4,"LI":2,"AD":2,"SV":3,"BY":5,"SR":1,"FO":2,"JE":1,"KW":2,"UZ":2,"GF":1,"AM":1,"VE":3,"CY":3,"IM":2,"QA":5,"KG":2,"SC":1,"SA":5,"VN":2,"AL":1,"LV":5,"OM":1,"BA":1,"AW":1,"PH":1,"EC":1}}