{"total":23397,"countries":{"null":15379,"AU":162,"DE":1312,"CA":357,"US":2301,"SE":83,"BR":109,"RO":23,"NL":343,"SG":128,"GB":291,"HK":47,"FI":377,"IE":42,"BE":43,"ES":93,"PR":7,"MD":11,"BZ":1,"AT":78,"FR":541,"KR":118,"JP":137,"RE":5,"HU":23,"CZ":100,"RU":189,"ID":28,"NO":35,"MY":18,"CH":232,"IN":44,"PL":65,"CN":40,"VN":6,"LT":41,"PH":4,"TW":32,"IT":95,"IS":13,"UA":34,"PT":21,"TH":30,"SC":1,"DK":16,"AR":19,"BG":35,"NZ":34,"AX":1,"CO":6,"TR":12,"CL":6,"IL":4,"AI":1,"SI":19,"JM":1,"BY":5,"BH":1,"SK":19,"ZA":29,"EE":8,"MX":18,"AE":21,"GR":8,"HR":9,"LU":10,"MT":4,"KW":1,"EC":2,"SR":1,"PA":3,"KZ":4,"DO":4,"LV":2,"UZ":2,"PE":1,"AD":2,"SV":3,"RS":3,"FO":2,"JE":1,"PY":1,"CR":5,"GE":2,"AL":1,"CY":3,"QA":4,"CW":2,"AM":2,"MU":1,"SA":5,"KG":2,"UY":4,"LI":2,"VE":2,"AW":1,"OM":1,"IR":1,"PK":1,"IM":1}}