{"total":23735,"countries":{"null":15531,"DE":1298,"US":2403,"BA":1,"CH":238,"SE":84,"CR":5,"FR":569,"MT":5,"NL":339,"FI":361,"SG":130,"GB":309,"MY":24,"UA":36,"IT":87,"IE":44,"IN":41,"UZ":2,"BR":99,"CZ":105,"MD":11,"TH":38,"BZ":1,"CA":373,"AT":84,"MX":26,"JP":137,"SA":7,"ES":101,"RU":186,"AU":162,"KR":114,"TW":33,"NO":39,"GR":7,"LT":37,"PL":68,"CN":45,"SK":21,"HU":28,"BE":48,"RE":4,"SI":16,"AE":21,"RS":4,"PA":3,"HK":48,"QA":5,"ME":1,"PT":25,"ZA":32,"TR":11,"VE":2,"ID":30,"AD":3,"IL":6,"NZ":32,"JM":1,"VN":6,"DO":5,"KZ":5,"EE":8,"IS":13,"BG":35,"AR":13,"HR":6,"UY":5,"RO":31,"DK":16,"IR":2,"LU":9,"NG":1,"CW":1,"AL":1,"AI":1,"BY":6,"TT":1,"KW":2,"CO":5,"KH":1,"SV":3,"LI":2,"PR":5,"FO":2,"JE":1,"AM":1,"CL":6,"LV":4,"IM":2,"CY":3,"EC":3,"SR":1,"PY":1,"BH":1,"SC":1,"AW":1,"PH":1,"MU":1,"KG":2}}