{"total":22994,"countries":{"null":15355,"TH":31,"DE":1288,"US":2215,"RO":23,"FR":549,"CA":349,"NL":326,"SG":103,"GB":260,"CH":223,"FI":361,"IE":43,"ES":106,"KW":2,"PR":3,"MD":11,"BZ":1,"AT":79,"JP":105,"AU":144,"CZ":103,"IT":94,"DK":17,"RU":185,"UA":38,"CO":5,"KR":101,"DO":4,"PL":68,"PT":19,"LT":38,"BR":87,"TW":18,"HU":26,"PH":2,"SE":81,"CN":41,"BE":30,"UZ":2,"HK":32,"NO":35,"HR":8,"CW":2,"AR":20,"NZ":30,"MX":21,"CL":6,"TR":11,"IL":5,"SK":20,"GR":8,"SI":17,"MY":20,"IN":18,"AE":17,"JM":1,"EE":8,"BG":39,"IS":15,"LU":9,"ZA":21,"ID":13,"MT":3,"AL":1,"EC":2,"CD":1,"VN":6,"PA":2,"KZ":5,"IM":2,"KG":2,"LV":3,"RE":4,"AD":2,"SV":3,"FO":2,"JE":1,"AI":1,"PK":1,"CR":5,"ME":1,"CY":3,"QA":5,"RS":3,"TT":1,"SC":1,"IR":1,"AM":1,"UY":4,"OM":1,"LI":2,"BY":5,"PY":1,"MU":1,"BA":1,"SA":2,"AW":1,"VE":2}}