{"total":23382,"countries":{"null":15346,"PL":67,"AU":164,"TH":33,"DE":1303,"CA":363,"US":2315,"SE":80,"BR":99,"RO":23,"NL":349,"SG":128,"GB":295,"FI":378,"IE":42,"ES":96,"SI":19,"PR":7,"CZ":97,"MD":11,"BZ":1,"AT":80,"FR":544,"KR":118,"JP":134,"RU":182,"UA":36,"NO":36,"CH":235,"CN":46,"VN":8,"LT":41,"PH":4,"TW":29,"IT":96,"IS":13,"HU":24,"UZ":2,"IN":39,"BE":41,"HK":48,"PT":21,"VE":3,"SC":1,"DK":16,"BG":39,"NZ":33,"AR":18,"AX":1,"ID":27,"TR":13,"CL":6,"IL":4,"AI":1,"JM":1,"BY":6,"CO":4,"GR":8,"SK":18,"ZA":31,"RE":5,"HR":7,"EE":8,"MX":16,"MY":19,"LU":10,"AM":2,"MT":4,"AE":21,"KW":1,"EC":2,"SR":1,"PA":3,"KZ":4,"UY":4,"DO":4,"LV":3,"AD":2,"SV":3,"RS":2,"FO":2,"JE":1,"PY":1,"CR":5,"GE":2,"AL":1,"CY":3,"QA":4,"CW":2,"PK":1,"SA":4,"MU":1,"BH":3,"KG":2,"LI":2,"AW":1,"OM":1,"IR":1,"IM":1}}