{"total":23617,"countries":{"null":15488,"US":2407,"DE":1274,"CA":377,"SE":84,"CR":5,"FR":557,"MT":5,"NL":334,"FI":358,"SG":128,"GB":301,"MY":23,"CH":230,"IN":42,"UA":35,"IT":93,"IE":44,"UZ":2,"BR":94,"CZ":102,"MD":10,"TH":39,"SK":19,"BZ":1,"AT":83,"HU":27,"JP":142,"SA":7,"BE":46,"ES":95,"RU":182,"AU":164,"KR":116,"NO":38,"GR":7,"LT":37,"PR":5,"TW":30,"PL":68,"CN":45,"HK":49,"RE":4,"MX":23,"ZA":29,"SI":16,"AE":20,"RS":4,"PA":2,"ID":29,"CD":1,"QA":5,"ME":1,"PT":22,"AR":15,"VE":2,"AD":3,"IL":7,"DK":15,"NZ":31,"JM":1,"VN":7,"DO":4,"KZ":5,"EE":8,"IS":13,"TR":10,"BG":36,"HR":5,"UY":6,"RO":31,"PY":2,"LU":9,"NG":1,"IR":2,"CW":1,"AL":1,"AI":1,"BY":7,"CO":5,"TT":1,"SV":3,"LI":2,"FO":2,"JE":1,"KW":2,"AM":1,"BH":2,"CL":5,"LV":4,"IM":2,"CY":3,"EC":3,"PH":2,"SR":1,"SC":1,"AW":1,"MU":1,"KG":2,"KH":1}}