{"total":23809,"countries":{"CH":241,"null":15392,"US":2406,"DE":1352,"SE":102,"FR":576,"GB":319,"MT":5,"CL":7,"NL":345,"FI":394,"SG":130,"ES":106,"BG":40,"TH":36,"UA":41,"IE":52,"AU":174,"BR":94,"HU":28,"CA":380,"CZ":106,"MD":12,"BZ":1,"AT":87,"PT":22,"JP":144,"IN":44,"RU":182,"KR":125,"IT":104,"SI":17,"MY":23,"LT":39,"CN":53,"TR":12,"TW":33,"BE":47,"ZA":33,"PL":65,"BY":7,"GR":6,"NO":37,"RO":28,"RS":5,"UY":5,"HK":52,"DK":16,"IS":10,"VE":2,"AD":3,"IL":5,"NZ":33,"EC":2,"SK":22,"JM":1,"ID":29,"MX":18,"VN":9,"DO":4,"KZ":4,"AR":18,"EE":8,"CO":6,"PA":2,"BA":1,"BH":6,"LU":9,"NG":1,"RE":2,"HR":8,"SA":5,"CR":6,"IR":2,"CW":2,"AL":1,"AE":19,"AM":1,"PH":4,"LI":2,"PR":3,"FO":2,"JE":1,"KW":2,"SV":3,"ME":2,"QA":4,"TT":1,"MU":1,"KH":1,"KG":2,"AI":1,"CY":3,"LV":3,"UZ":1,"SR":1,"PY":1,"SC":1,"AW":1,"IM":2,"OM":1,"PK":1,"PE":1}}