{"total":23663,"countries":{"null":15529,"US":2371,"DE":1302,"FR":568,"IT":88,"MT":4,"NL":342,"GB":297,"CA":357,"SG":130,"MY":18,"FI":377,"IE":42,"CZ":96,"MD":10,"KR":120,"ID":25,"BZ":1,"AT":86,"TH":36,"JP":139,"SE":83,"AU":155,"ES":114,"IN":40,"RU":175,"MU":1,"CH":246,"PL":67,"BR":101,"BG":37,"LT":39,"TW":34,"RS":5,"UA":33,"HU":26,"SK":23,"AE":19,"BE":45,"NZ":29,"CO":6,"NO":39,"CN":47,"CW":2,"RO":33,"HR":8,"AR":18,"HK":44,"QA":5,"ME":1,"PT":20,"VE":2,"UY":5,"MX":22,"AD":2,"IL":5,"BA":1,"IR":1,"JM":1,"EE":8,"ZA":24,"BY":7,"DO":5,"IS":14,"TR":12,"DK":17,"PR":7,"GR":6,"KG":1,"LU":10,"CR":5,"RE":4,"SI":15,"KW":2,"PA":2,"KZ":5,"SA":5,"LI":2,"SV":3,"FO":2,"JE":1,"CL":6,"UZ":2,"AM":1,"CY":3,"AI":1,"NG":1,"VN":4,"IM":3,"LV":4,"PY":1,"AL":1,"NP":1,"GF":1,"SC":1,"AW":1,"BH":1,"PH":1,"KH":1}}