{"total":23686,"countries":{"null":15505,"TH":35,"DE":1310,"SE":90,"CA":367,"CR":5,"US":2384,"FR":558,"MT":4,"NL":338,"SG":125,"GB":291,"MY":22,"IS":13,"BR":106,"ZA":31,"FI":379,"IE":43,"TR":11,"VN":4,"CZ":99,"MD":11,"KR":116,"ES":112,"BZ":1,"AT":84,"IT":96,"AU":161,"NZ":32,"JP":136,"RU":182,"KW":2,"CH":241,"GR":7,"LT":39,"TW":35,"MX":24,"UA":35,"HU":26,"SK":23,"BE":45,"CN":38,"PY":1,"HK":49,"CO":3,"NO":38,"IN":43,"AE":19,"CW":2,"PA":3,"SA":6,"BG":40,"AR":22,"QA":5,"ME":1,"PT":24,"VE":2,"PL":67,"AD":2,"IL":4,"BA":1,"ID":28,"IR":2,"JM":1,"EE":8,"BD":1,"DO":4,"RO":27,"SI":15,"DK":17,"PR":4,"KG":1,"LU":9,"UY":6,"CL":6,"TT":1,"KZ":4,"HR":8,"LI":2,"RE":4,"SV":3,"FO":2,"JE":1,"UZ":2,"BH":1,"KH":1,"AM":1,"CY":3,"RS":2,"LV":4,"PH":3,"NG":1,"GF":1,"IM":2,"AL":1,"AI":1,"NP":1,"BY":6,"SR":1,"SC":1,"AW":1,"PE":1}}